linesieve/__init__.py
linesieve/__main__.py
linesieve/cli.py
linesieve/click_utils.py
linesieve/parsing.py
linesieve/paths.py
linesieve-1.0.dist-info/LICENSE
linesieve-1.0.dist-info/METADATA
linesieve-1.0.dist-info/WHEEL
linesieve-1.0.dist-info/entry_points.txt
linesieve-1.0.dist-info/top_level.txt
linesieve-1.0.dist-info/RECORD
