Metadata-Version: 2.1
Name: linesieve
Version: 1.0
Summary: An unholy blend of grep, sed, awk, and Python.
Home-page: https://github.com/lemon24/linesieve
Author: lemon24
License: BSD-3-Clause
Project-URL: Documentation, https://linesieve.readthedocs.io/
Project-URL: Issue Tracker, https://github.com/lemon24/linesieve/issues
Project-URL: Source Code, https://github.com/lemon24/linesieve
Keywords: grep,sed,awk,cli,command-line,terminal,text,text processing,search,replace,regex
Classifier: Development Status :: 5 - Production/Stable
Classifier: Environment :: Console
Classifier: Intended Audience :: Developers
Classifier: Intended Audience :: System Administrators
Classifier: License :: OSI Approved :: BSD License
Classifier: Operating System :: OS Independent
Classifier: Programming Language :: Python
Classifier: Programming Language :: Python :: 3
Classifier: Programming Language :: Python :: 3 :: Only
Classifier: Topic :: Internet :: Log Analysis
Classifier: Topic :: System :: Shells
Classifier: Topic :: System :: Systems Administration
Classifier: Topic :: Text Processing
Classifier: Topic :: Text Processing :: Filters
Classifier: Topic :: Utilities
Requires-Python: >=3.8
License-File: LICENSE
Requires-Dist: click (>=8)
Requires-Dist: braceexpand (>=0.1)
Provides-Extra: dev
Requires-Dist: pre-commit ; extra == 'dev'
Requires-Dist: build ; extra == 'dev'
Requires-Dist: twine ; extra == 'dev'
Provides-Extra: docs
Requires-Dist: sphinx ; extra == 'docs'
Requires-Dist: sphinx-rtd-theme ; extra == 'docs'
Requires-Dist: sphinx-click ; extra == 'docs'
Provides-Extra: tests
Requires-Dist: pytest ; extra == 'tests'
Requires-Dist: pytest-cov ; extra == 'tests'
